covid19sweden/__init__.py
covid19sweden/backup.py
covid19sweden/fohm.py
covid19sweden/main.py
covid19sweden/scb.py
covid19sweden/data/deaths.csv
covid19sweden-0.2.2.dist-info/LICENSE
covid19sweden-0.2.2.dist-info/METADATA
covid19sweden-0.2.2.dist-info/WHEEL
covid19sweden-0.2.2.dist-info/top_level.txt
covid19sweden-0.2.2.dist-info/RECORD
