Metadata-Version: 2.1
Name: covid19sweden
Version: 0.2.2
Summary: Web Scraper for Sweden COVID19 data.
Home-page: https://github.com/martinbenes1996/covid19sweden
Author: Martin Beneš
Author-email: martinbenes1996@gmail.com
License: MPL
Download-URL: https://github.com/martinbenes1996/covid19sweden/archive/0.2.2.tar.gz
Keywords: 2019-nCov,sweden,coronavirus,covid-19,covid-data,covid19-data
Platform: UNKNOWN
Classifier: Development Status :: 3 - Alpha
Classifier: Intended Audience :: Science/Research
Classifier: Intended Audience :: Developers
Classifier: Intended Audience :: Other Audience
Classifier: Topic :: Database
Classifier: Topic :: Scientific/Engineering
Classifier: Topic :: Scientific/Engineering :: Information Analysis
Classifier: Topic :: Software Development :: Libraries
Classifier: Topic :: Utilities
Classifier: License :: OSI Approved :: Mozilla Public License 2.0 (MPL 2.0)
Classifier: Programming Language :: Python :: 3
Classifier: Programming Language :: Python :: 3.4
Classifier: Programming Language :: Python :: 3.5
Classifier: Programming Language :: Python :: 3.6
Requires-Dist: pandas
Requires-Dist: openpyxl
Requires-Dist: requests
